{
  "portfolio_id": "alpha-paper-001",
  "created_at": "2026-07-21T00:00:00Z",
  "initial_capital": 10000,
  "current_value": 10003.89832224296,
  "cash": 2551.753413762959,
  "positions": [
    {
      "ticker": "COIN",
      "shares": 9,
      "entryPrice": 160.42999,
      "currentPrice": 160.42999,
      "stopLoss": 112.3,
      "takeProfit": 243.97,
      "entryDate": "2026-07-20T23:36:03.333Z",
      "unrealizedPnl": 0,
      "unrealizedPnlPct": 0
    },
    {
      "ticker": "SOL",
      "shares": 16,
      "entryPrice": 77.71,
      "currentPrice": 78.1,
      "stopLoss": 58.28,
      "takeProfit": 117.29,
      "entryDate": "2026-07-20T23:36:03.345Z",
      "unrealizedPnl": 6.240000000000009,
      "unrealizedPnlPct": 0.5018659117230762
    },
    {
      "ticker": "CRWD",
      "shares": 5,
      "entryPrice": 198.49001,
      "currentPrice": 198.49001,
      "stopLoss": 163.75,
      "takeProfit": 297.95,
      "entryDate": "2026-07-20T23:36:03.351Z",
      "unrealizedPnl": 0,
      "unrealizedPnlPct": 0
    },
    {
      "ticker": "TSLA",
      "shares": 2,
      "entryPrice": 369.57001,
      "currentPrice": 369.57001,
      "stopLoss": 277.18,
      "takeProfit": 635.92,
      "entryDate": "2026-07-21T00:31:54.791Z",
      "unrealizedPnl": 0,
      "unrealizedPnlPct": 0
    },
    {
      "ticker": "HIMS",
      "shares": 25,
      "entryPrice": 32.7,
      "currentPrice": 32.7,
      "stopLoss": 23.71,
      "takeProfit": 50.76,
      "entryDate": "2026-07-21T00:33:14.652Z",
      "unrealizedPnl": 0,
      "unrealizedPnlPct": 0
    },
    {
      "ticker": "MSTR",
      "shares": 7,
      "entryPrice": 97.82,
      "currentPrice": 97.82,
      "stopLoss": 75.81,
      "takeProfit": 136.41,
      "entryDate": "2026-07-21T00:33:14.663Z",
      "unrealizedPnl": 0,
      "unrealizedPnlPct": 0
    },
    {
      "ticker": "PLTR",
      "shares": 4,
      "entryPrice": 134.85001,
      "currentPrice": 134.85001,
      "stopLoss": 97.77,
      "takeProfit": 210.4,
      "entryDate": "2026-07-21T10:36:28.877Z",
      "unrealizedPnl": -0.53940004
    },
    {
      "ticker": "ETH",
      "shares": 0.274536,
      "entryPrice": 1930.39,
      "currentPrice": 1934.68,
      "stopLoss": 1592.57,
      "takeProfit": 2516.99,
      "entryDate": "2026-07-21T11:36:41.510Z",
      "unrealizedPnl": 1.17775943999999,
      "unrealizedPnlPct": 0.22223488517865153
    },
    {
      "ticker": "BTC",
      "shares": 0.006802,
      "entryPrice": 66214,
      "currentPrice": 66790,
      "stopLoss": 56281.9,
      "takeProfit": 83462.56,
      "entryDate": "2026-07-21T11:36:41.521Z",
      "unrealizedPnl": 3.917952,
      "unrealizedPnlPct": 0.8699066662639421
    }
  ],
  "trades": [
    {
      "id": "T1784590563329",
      "timestamp": "2026-07-20T23:36:03.329Z",
      "ticker": "COIN",
      "action": "BUY",
      "shares": 9,
      "price": 160.42999,
      "total": 1443.8699100000001,
      "commission": 1.44386991,
      "reason": "COIN - momentum setup (2.1% move)",
      "stopLoss": 112.3,
      "takeProfit": 243.97
    },
    {
      "id": "T1784590563345",
      "timestamp": "2026-07-20T23:36:03.345Z",
      "ticker": "SOL",
      "action": "BUY",
      "shares": 16,
      "price": 77.71,
      "total": 1243.36,
      "commission": 1.24336,
      "reason": "SOL - momentum setup (1.9% move)",
      "stopLoss": 58.28,
      "takeProfit": 117.29
    },
    {
      "id": "T1784590563351",
      "timestamp": "2026-07-20T23:36:03.351Z",
      "ticker": "CRWD",
      "action": "BUY",
      "shares": 5,
      "price": 198.49001,
      "total": 992.45005,
      "commission": 0.9924500500000001,
      "reason": "CRWD - oversold setup (2.3% move)",
      "stopLoss": 163.75,
      "takeProfit": 297.95
    },
    {
      "id": "T1784593914787",
      "timestamp": "2026-07-21T00:31:54.787Z",
      "ticker": "TSLA",
      "action": "BUY",
      "shares": 2,
      "price": 369.57001,
      "total": 739.14002,
      "commission": 0.7391400200000001,
      "reason": "TSLA - oversold setup (3.0% move)",
      "stopLoss": 277.18,
      "takeProfit": 635.92
    },
    {
      "id": "T1784630188873",
      "timestamp": "2026-07-21T10:36:28.873Z",
      "ticker": "PLTR",
      "action": "BUY",
      "shares": 4,
      "price": 134.85001,
      "total": 539.40004,
      "commission": 0.53940004,
      "reason": "PLTR - momentum setup (1.9% move)",
      "stopLoss": 97.77,
      "takeProfit": 210.4
    },
    {
      "id": "T1784633801507",
      "timestamp": "2026-07-21T11:36:41.507Z",
      "ticker": "ETH",
      "action": "BUY",
      "shares": 0.274536,
      "price": 1930.39,
      "total": 529.96154904,
      "commission": 0.52996154904,
      "reason": "ETH - momentum setup (2.1% move)",
      "stopLoss": 1592.57,
      "takeProfit": 2516.99
    },
    {
      "id": "T1784633801521",
      "timestamp": "2026-07-21T11:36:41.521Z",
      "ticker": "BTC",
      "action": "BUY",
      "shares": 0.006802,
      "price": 66214,
      "total": 450.387628,
      "commission": 0.45038762800000004,
      "reason": "BTC - momentum setup (2.2% move)",
      "stopLoss": 56281.9,
      "takeProfit": 83462.56
    }
  ],
  "performance": {
    "total_return": 0.038983222429589404,
    "total_trades": 9,
    "winning_trades": 0,
    "losing_trades": 0,
    "win_rate": 0,
    "avg_winner": 0,
    "avg_loser": 0,
    "max_drawdown": 0.05597639980000167
  },
  "daily_snapshots": [
    {
      "date": "2026-07-20",
      "value": 9996.320320039998,
      "cash": 6316.640360039999,
      "unrealized_pnl": 0,
      "positions_count": 3
    },
    {
      "date": "2026-07-21",
      "value": 10004.82,
      "cash": 2551.75,
      "unrealized_pnl": 12.72,
      "positions_count": 7,
      "timestamp": "2026-07-21T15:36:00Z"
    }
  ]
}